{"name":"MIS_TimeSheet_ConfTimesheet_verifySave","id":"perform-actions-on-timesheet-of-mis-website;mis-timesheet-conftimesheet-verifysave","testSteps":[{"number":1,"description":"Given Navigate to MIS Beta Application","duration":2136,"startTime":"2022-09-28T20:08:40.374+05:30[Asia/Calcutta]","result":"SUCCESS","precondition":false,"level":0},{"number":2,"description":"And Login to MIS with credentials \"amisha.srivastava\" \"Gemini@1234\"","duration":2718,"startTime":"2022-09-28T20:08:42.511+05:30[Asia/Calcutta]","result":"SUCCESS","precondition":false,"level":0},{"number":3,"description":"Then Open \"Configure Timesheet\" page of \"TimeSheet\" module","duration":7657,"startTime":"2022-09-28T20:08:45.230+05:30[Asia/Calcutta]","result":"SUCCESS","precondition":false,"level":0},{"number":4,"description":"And Verify \"Configure Timesheet\" page of type \"Sub\"","duration":934,"startTime":"2022-09-28T20:08:52.889+05:30[Asia/Calcutta]","result":"SUCCESS","precondition":false,"level":0},{"number":5,"description":"And Click on save button","duration":287,"startTime":"2022-09-28T20:08:53.823+05:30[Asia/Calcutta]","result":"SUCCESS","precondition":false,"level":0},{"number":6,"description":"And Verify and accept success popup","duration":2730,"startTime":"2022-09-28T20:08:54.110+05:30[Asia/Calcutta]","result":"SUCCESS","precondition":false,"level":0},{"number":7,"description":"Then Logout from MIS","duration":789,"startTime":"2022-09-28T20:08:56.856+05:30[Asia/Calcutta]","result":"SUCCESS","precondition":false,"level":0}],"userStory":{"id":"perform-actions-on-timesheet-of-mis-website","storyName":"Perform actions on Timesheet of MIS website","displayName":"Perform actions on Timesheet of MIS website","path":"Timesheet.feature","type":"feature"},"featureTag":{"name":"Perform actions on Timesheet of MIS website","type":"feature","displayName":"Perform actions on Timesheet of MIS website"},"title":"MIS time sheet conf timesheet verify save","description":"","backgroundTitle":"","backgroundDescription":"","tags":[{"name":"ConfTimesheet","type":"tag","displayName":"ConfTimesheet"},{"name":"Perform actions on Timesheet of MIS website","type":"feature","displayName":"Perform actions on Timesheet of MIS website"},{"name":"TC03","type":"tag","displayName":"TC03"},{"name":"Test","type":"tag","displayName":"Test"},{"name":"TimeSheet","type":"tag","displayName":"TimeSheet"}],"startTime":"2022-09-28T20:08:40.374+05:30[Asia/Calcutta]","duration":17272,"projectKey":"","sessionId":"181ed25fa44160de2e3031935d66192c","driver":"chrome","isManualTestingUpToDate":false,"manual":false,"testSource":"Cucumber","result":"SUCCESS"}